resim/actor/state/proto/observable_state_pb2.py
resim/actor/state/proto/trajectory_pb2.py
resim/auth/python/device_code_client.py
resim/auth/python/username_password_client.py
resim/curves/proto/t_curve_pb2.py
resim/curves/proto/two_jet_pb2.py
resim/experiences/proto/actor_pb2.py
resim/experiences/proto/completion_criteria_pb2.py
resim/experiences/proto/dynamic_behavior_pb2.py
resim/experiences/proto/experience_pb2.py
resim/experiences/proto/geometry_pb2.py
resim/experiences/proto/ilqr_drone_pb2.py
resim/experiences/proto/location_condition_pb2.py
resim/experiences/proto/revision_pb2.py
resim/experiences/proto/storyboard_pb2.py
resim/geometry/proto/oriented_box_pb2.py
resim/geometry/proto/wireframe_pb2.py
resim/geometry/python/box_box_distance_python.pyi
resim/geometry/python/oriented_box_python.pyi
resim/geometry/python/polygon_distance_python.pyi
resim/geometry/python/polygon_distance_python.so
resim/metrics/default_report_metrics
resim/metrics/default_report_metrics.py
resim/metrics/dice_coefficient.py
resim/metrics/fetch_all_pages.py
resim/metrics/fetch_job_metrics.py
resim/metrics/fetch_metrics_urls.py
resim/metrics/fetch_report_metrics.py
resim/metrics/fetch_sweep_metrics
resim/metrics/fetch_sweep_metrics.py
resim/metrics/get_metrics_proto.py
resim/metrics/proto/metrics_pb2.py
resim/metrics/proto/validate_metrics_proto.py
resim/metrics/python/emissions.py
resim/metrics/python/metrics.py
resim/metrics/python/metrics_utils.py
resim/metrics/python/metrics_writer.py
resim/metrics/python/plotly_helpers.py
resim/metrics/python/unpack_metrics.py
resim/metrics/resim_style.py
resim/msg/detection_pb2.py
resim/msg/header_pb2.py
resim/msg/navsat_pb2.py
resim/msg/odometry_pb2.py
resim/msg/pose_pb2.py
resim/msg/primitives_pb2.py
resim/msg/transform_pb2.py
resim/orchestration/kickoff_report.py
resim/py.typed
resim/sdk/__init__.py
resim/sdk/auth/__init__.py
resim/sdk/auth/check_expiration.py
resim/sdk/auth/const.py
resim/sdk/auth/device_code_client.py
resim_open_core-1.0.1.dist-info/WHEEL
resim_open_core-1.0.1.dist-info/METADATA
resim_open_core-1.0.1.dist-info/RECORD
