Metadata-Version: 2.1
Name: resim-open-core
Author: ReSim Developers
Home-page: https://www.resim.ai/
License: Copyright 2025 ReSim, Inc.
Summary: ReSim Metrics Libraries.
Classifier: License :: OSI Approved :: MIT License
Requires-Dist: numpy>=1.25.2
Requires-Dist: pandas<3,>=1.5.3
Requires-Dist: plotly>=5.22.0
Requires-Dist: PyYAML>=6.0.0
Requires-Dist: requests>=2.31.0
Requires-Dist: httpx>=0.25.2
Requires-Dist: typing-extensions>=4.10.0
Requires-Dist: attrs>=22.2.0
Requires-Dist: python-dateutil<3.0.0,>=2.8.1
Requires-Dist: httpx<0.29.0,>=0.20.0
Requires-Dist: numpy>=1.25.2
Requires-Dist: PyYAML>=6.0.0
Requires-Dist: httpx>=0.25.2
Requires-Dist: protobuf>=5.29.5
Version: 1.0.1
